{"requestResult":{"listLine":[{"endLineCode":"4HN013","lineCode":"HDG351_4HN013","lineId":41144,"startLineCode":"4HN013","status":0},{"endLineCode":"NAN384","lineCode":"NAN386_NAN384","lineId":41162,"startLineCode":"NAN386","status":0},{"endLineCode":"HDG005","lineCode":"DNG243_HDG005","lineId":143527,"startLineCode":"DNG243","status":0},{"endLineCode":"DNG061","lineCode":"DNG081_DNG061","lineId":153378,"startLineCode":"DNG081","status":0},{"endLineCode":"DNG102","lineCode":"DNG088_DNG102","lineId":153379,"startLineCode":"DNG088","status":0},{"endLineCode":"DNG088","lineCode":"DNG075_DNG088","lineId":153381,"startLineCode":"DNG075","status":0},{"endLineCode":"DNG010","lineCode":"DNG065_DNG010","lineId":153397,"startLineCode":"DNG065","status":0},{"endLineCode":"DNG059","lineCode":"DNG084_DNG059","lineId":153846,"startLineCode":"DNG084","status":0},{"endLineCode":"DNG047","lineCode":"DNG104_DNG047","lineId":153850,"startLineCode":"DNG104","status":0},{"endLineCode":"DNG004","lineCode":"DNG039_DNG004","lineId":153858,"startLineCode":"DNG039","status":0}],"status":"Success"}}